Metadata-Version: 2.1
Name: circuitpython-MorseCode
Version: 0.2.0
Summary: Morse Code Library for CircuitPython
Home-page: https://github.com/jposada202020/CircuitPython_MorseCode.git
Author: Jose David M.
Author-email: 
License: MIT
Keywords: adafruit blinka circuitpython micropython morse code
Platform: UNKNOWN
Classifier: Development Status :: 3 - Alpha
Classifier: Intended Audience :: Developers
Classifier: Topic :: Software Development :: Libraries
Classifier: Topic :: System :: Hardware
Classifier: License :: OSI Approved :: MIT License
Classifier: Programming Language :: Python :: 3
Classifier: Programming Language :: Python :: 3.4
Classifier: Programming Language :: Python :: 3.5
